scietex/hal/serial/__init__.py
scietex/hal/serial/py.typed
scietex/hal/serial/version.py
scietex/hal/serial/client/__init__.py
scietex/hal/serial/client/rs485_client.py
scietex/hal/serial/config/__init__.py
scietex/hal/serial/config/defaults.py
scietex/hal/serial/config/exceptions.py
scietex/hal/serial/config/serial_connection_implementation.py
scietex/hal/serial/config/serial_connection_interface.py
scietex/hal/serial/config/validation.py
scietex/hal/serial/server/__init__.py
scietex/hal/serial/server/modbus_datablock.py
scietex/hal/serial/server/rs485_server.py
scietex/hal/serial/utilities/__init__.py
scietex/hal/serial/utilities/checksum.py
scietex/hal/serial/utilities/mock.py
scietex/hal/serial/utilities/modbus.py
scietex/hal/serial/utilities/numeric.py
scietex/hal/serial/utilities/serial_port_finder.py
scietex/hal/serial/virtual/__init__.py
scietex/hal/serial/virtual/virtual_serial_network.py
scietex/hal/serial/virtual/virtual_serial_pair.py
scietex/hal/serial/virtual/worker.py
scietex_hal_serial-1.1.0.dist-info/licenses/LICENSE
scietex_hal_serial-1.1.0.dist-info/METADATA
scietex_hal_serial-1.1.0.dist-info/WHEEL
scietex_hal_serial-1.1.0.dist-info/top_level.txt
scietex_hal_serial-1.1.0.dist-info/RECORD
