Metadata-Version: 2.4
Name: scietex.hal.serial
Version: 1.1.0
Summary: Scietex Serial Communication Library
Author-email: Anton Bondarenko <bond.anton@gmail.com>
License: MIT License
Project-URL: Homepage, https://github.com/bond-anton/scietex.hal.serial
Project-URL: Bug Tracker, https://github.com/bond-anton/scietex.hal.serial/issues
Classifier: Programming Language :: Python :: 3
Classifier: License :: OSI Approved :: MIT License
Classifier: Operating System :: OS Independent
Requires-Python: >=3.10
License-File: LICENSE
Requires-Dist: pymodbus[serial]>=3.11.4
Provides-Extra: dev
Provides-Extra: test
Requires-Dist: flake8; extra == "test"
Requires-Dist: pytest; extra == "test"
Requires-Dist: pytest-asyncio; extra == "test"
Provides-Extra: lint
Requires-Dist: pylint; extra == "lint"
Dynamic: license-file
